{
  "name" : "C. News Distribution",
  "testType" : "SINGLE",
  "input" : {
    "type" : "STANDARD",
    "fileName" : "input.txt"
  },
  "output" : {
    "type" : "STANDARD",
    "fileName" : "output.txt"
  },
  "tests" : [ {
    "input" : "7 5\n3 2 5 4\n0\n2 1 2\n1 1\n2 6 7\n",
    "output" : "4 4 1 4 4 2 2 \n",
    "index" : 0,
    "active" : true
  } ],
  "location" : "src/Codes",
  "vmArgs" : "-Xmx256M",
  "mainClass" : "Main",
  "taskClass" : "Codes.CNewsDistribution",
  "checkerClass" : "net.egork.chelper.checkers.TokenChecker",
  "checkerParameters" : "",
  "testClasses" : [ ],
  "date" : "2019.05.16",
  "contestName" : "Educational Codeforces Round 65 (Rated for Div. 2)",
  "truncate" : true,
  "inputClass" : "FastIO.inputClass",
  "outputClass" : "java.io.PrintWriter",
  "includeLocale" : false,
  "failOnOverflow" : false,
  "interactive" : false,
  "interactor" : "net.egork.chelper.tester.Interactor"
}